fiuai_s3/__init__.py
fiuai_s3/object_storage.py
fiuai_s3/type.py
fiuai_s3/alicloud/__init__.py
fiuai_s3/alicloud/alicloud_storage.py
fiuai_s3/minio/__init__.py
fiuai_s3/minio/minio_storage.py
fiuai_s3-0.5.0.dist-info/METADATA
fiuai_s3-0.5.0.dist-info/WHEEL
fiuai_s3-0.5.0.dist-info/licenses/LICENSE
fiuai_s3-0.5.0.dist-info/RECORD
