Metadata-Version: 2.4
Name: fiuai-s3
Version: 0.5.0
Summary: 一个支持阿里云OSS和MinIO的对象存储抽象包
Project-URL: Homepage, https://github.com/fiuai-sz/fiuai-s3
Project-URL: Repository, https://github.com/fiuai-sz/fiuai-s3.git
Author-email: liming <lmlala@aliyun.com>
License:                                  Apache License
License-File: LICENSE
Classifier: Development Status :: 3 - Alpha
Classifier: Intended Audience :: Developers
Classifier: License :: OSI Approved :: MIT License
Classifier: Operating System :: OS Independent
Classifier: Programming Language :: Python :: 3
Classifier: Programming Language :: Python :: 3.7
Classifier: Programming Language :: Python :: 3.8
Classifier: Programming Language :: Python :: 3.9
Classifier: Programming Language :: Python :: 3.10
Requires-Python: >=3.7
Requires-Dist: hatch>=1.7.0
Requires-Dist: minio>=7.1.0
Requires-Dist: oss2>=2.15.0
Requires-Dist: pydantic>=1.8.0
